{"nodes": [{"id": "c_users_athar_downloads_model_doc_app_py", "label": "app.py", "file_type": "code", "source_file": "C:\\Users\\athar\\Downloads\\Model Doc\\app.py", "source_location": "L1"}, {"id": "app_init_local_stack", "label": "init_local_stack()", "file_type": "code", "source_file": "C:\\Users\\athar\\Downloads\\Model Doc\\app.py", "source_location": "L355"}, {"id": "app_get_feedback_collector", "label": "get_feedback_collector()", "file_type": "code", "source_file": "C:\\Users\\athar\\Downloads\\Model Doc\\app.py", "source_location": "L375"}, {"id": "app_load_rag_chunk_count", "label": "_load_rag_chunk_count()", "file_type": "code", "source_file": "C:\\Users\\athar\\Downloads\\Model Doc\\app.py", "source_location": "L380"}, {"id": "app_get_runtime_status", "label": "get_runtime_status()", "file_type": "code", "source_file": "C:\\Users\\athar\\Downloads\\Model Doc\\app.py", "source_location": "L395"}, {"id": "app_render_section_intro", "label": "render_section_intro()", "file_type": "code", "source_file": "C:\\Users\\athar\\Downloads\\Model Doc\\app.py", "source_location": "L425"}, {"id": "app_render_sidebar_status", "label": "render_sidebar_status()", "file_type": "code", "source_file": "C:\\Users\\athar\\Downloads\\Model Doc\\app.py", "source_location": "L438"}, {"id": "app_render_hero", "label": "render_hero()", "file_type": "code", "source_file": "C:\\Users\\athar\\Downloads\\Model Doc\\app.py", "source_location": "L464"}, {"id": "app_render_result_banner", "label": "render_result_banner()", "file_type": "code", "source_file": "C:\\Users\\athar\\Downloads\\Model Doc\\app.py", "source_location": "L508"}, {"id": "app_render_capture_tips", "label": "render_capture_tips()", "file_type": "code", "source_file": "C:\\Users\\athar\\Downloads\\Model Doc\\app.py", "source_location": "L534"}, {"id": "app_render_fast_hosted_demo", "label": "render_fast_hosted_demo()", "file_type": "code", "source_file": "C:\\Users\\athar\\Downloads\\Model Doc\\app.py", "source_location": "L552"}, {"id": "app_rationale_1", "label": "Streamlit UI for Ragi Quality Grading System - \"Millets Now\" ==================", "file_type": "rationale", "source_file": "C:\\Users\\athar\\Downloads\\Model Doc\\app.py", "source_location": "L1"}, {"id": "app_rationale_356", "label": "Initialize the local physics extractor and Vision-RAG pipeline on demand.", "file_type": "rationale", "source_file": "C:\\Users\\athar\\Downloads\\Model Doc\\app.py", "source_location": "L356"}, {"id": "app_rationale_376", "label": "Keep feedback storage available without booting the local model stack.", "file_type": "rationale", "source_file": "C:\\Users\\athar\\Downloads\\Model Doc\\app.py", "source_location": "L376"}, {"id": "app_rationale_396", "label": "Return runtime and knowledge-base status for the UI.", "file_type": "rationale", "source_file": "C:\\Users\\athar\\Downloads\\Model Doc\\app.py", "source_location": "L396"}, {"id": "app_rationale_553", "label": "Embed the hosted demo for the lowest-latency path.", "file_type": "rationale", "source_file": "C:\\Users\\athar\\Downloads\\Model Doc\\app.py", "source_location": "L553"}], "edges": [{"source": "c_users_athar_downloads_model_doc_app_py", "target": "streamlit", "relation": "imports", "confidence": "EXTRACTED", "source_file": "C:\\Users\\athar\\Downloads\\Model Doc\\app.py", "source_location": "L20", "weight": 1.0}, {"source": "c_users_athar_downloads_model_doc_app_py", "target": "streamlit_components_v1", "relation": "imports", "confidence": "EXTRACTED", "source_file": "C:\\Users\\athar\\Downloads\\Model Doc\\app.py", "source_location": "L21", "weight": 1.0}, {"source": "c_users_athar_downloads_model_doc_app_py", "target": "os", "relation": "imports", "confidence": "EXTRACTED", "source_file": "C:\\Users\\athar\\Downloads\\Model Doc\\app.py", "source_location": "L22", "weight": 1.0}, {"source": "c_users_athar_downloads_model_doc_app_py", "target": "json", "relation": "imports", "confidence": "EXTRACTED", "source_file": "C:\\Users\\athar\\Downloads\\Model Doc\\app.py", "source_location": "L23", "weight": 1.0}, {"source": "c_users_athar_downloads_model_doc_app_py", "target": "html", "relation": "imports", "confidence": "EXTRACTED", "source_file": "C:\\Users\\athar\\Downloads\\Model Doc\\app.py", "source_location": "L24", "weight": 1.0}, {"source": "c_users_athar_downloads_model_doc_app_py", "target": "logging", "relation": "imports", "confidence": "EXTRACTED", "source_file": "C:\\Users\\athar\\Downloads\\Model Doc\\app.py", "source_location": "L25", "weight": 1.0}, {"source": "c_users_athar_downloads_model_doc_app_py", "target": "datetime", "relation": "imports_from", "confidence": "EXTRACTED", "source_file": "C:\\Users\\athar\\Downloads\\Model Doc\\app.py", "source_location": "L26", "weight": 1.0}, {"source": "c_users_athar_downloads_model_doc_app_py", "target": "pathlib", "relation": "imports_from", "confidence": "EXTRACTED", "source_file": "C:\\Users\\athar\\Downloads\\Model Doc\\app.py", "source_location": "L27", "weight": 1.0}, {"source": "c_users_athar_downloads_model_doc_app_py", "target": "typing", "relation": "imports_from", "confidence": "EXTRACTED", "source_file": "C:\\Users\\athar\\Downloads\\Model Doc\\app.py", "source_location": "L28", "weight": 1.0}, {"source": "c_users_athar_downloads_model_doc_app_py", "target": "tempfile", "relation": "imports", "confidence": "EXTRACTED", "source_file": "C:\\Users\\athar\\Downloads\\Model Doc\\app.py", "source_location": "L29", "weight": 1.0}, {"source": "c_users_athar_downloads_model_doc_app_py", "target": "dotenv", "relation": "imports_from", "confidence": "EXTRACTED", "source_file": "C:\\Users\\athar\\Downloads\\Model Doc\\app.py", "source_location": "L30", "weight": 1.0}, {"source": "c_users_athar_downloads_model_doc_app_py", "target": "cv2", "relation": "imports", "confidence": "EXTRACTED", "source_file": "C:\\Users\\athar\\Downloads\\Model Doc\\app.py", "source_location": "L32", "weight": 1.0}, {"source": "c_users_athar_downloads_model_doc_app_py", "target": "httpx", "relation": "imports", "confidence": "EXTRACTED", "source_file": "C:\\Users\\athar\\Downloads\\Model Doc\\app.py", "source_location": "L33", "weight": 1.0}, {"source": "c_users_athar_downloads_model_doc_app_py", "target": "numpy", "relation": "imports", "confidence": "EXTRACTED", "source_file": "C:\\Users\\athar\\Downloads\\Model Doc\\app.py", "source_location": "L34", "weight": 1.0}, {"source": "c_users_athar_downloads_model_doc_app_py", "target": "pandas", "relation": "imports", "confidence": "EXTRACTED", "source_file": "C:\\Users\\athar\\Downloads\\Model Doc\\app.py", "source_location": "L35", "weight": 1.0}, {"source": "c_users_athar_downloads_model_doc_app_py", "target": "pil", "relation": "imports_from", "confidence": "EXTRACTED", "source_file": "C:\\Users\\athar\\Downloads\\Model Doc\\app.py", "source_location": "L36", "weight": 1.0}, {"source": "c_users_athar_downloads_model_doc_app_py", "target": "physics_proxies", "relation": "imports_from", "confidence": "EXTRACTED", "source_file": "C:\\Users\\athar\\Downloads\\Model Doc\\app.py", "source_location": "L42", "weight": 1.0}, {"source": "c_users_athar_downloads_model_doc_app_py", "target": "vision_rag_pipeline", "relation": "imports_from", "confidence": "EXTRACTED", "source_file": "C:\\Users\\athar\\Downloads\\Model Doc\\app.py", "source_location": "L43", "weight": 1.0}, {"source": "c_users_athar_downloads_model_doc_app_py", "target": "lora_finetune", "relation": "imports_from", "confidence": "EXTRACTED", "source_file": "C:\\Users\\athar\\Downloads\\Model Doc\\app.py", "source_location": "L44", "weight": 1.0}, {"source": "c_users_athar_downloads_model_doc_app_py", "target": "app_init_local_stack", "relation": "contains", "confidence": "EXTRACTED", "source_file": "C:\\Users\\athar\\Downloads\\Model Doc\\app.py", "source_location": "L355", "weight": 1.0}, {"source": "c_users_athar_downloads_model_doc_app_py", "target": "app_get_feedback_collector", "relation": "contains", "confidence": "EXTRACTED", "source_file": "C:\\Users\\athar\\Downloads\\Model Doc\\app.py", "source_location": "L375", "weight": 1.0}, {"source": "c_users_athar_downloads_model_doc_app_py", "target": "app_load_rag_chunk_count", "relation": "contains", "confidence": "EXTRACTED", "source_file": "C:\\Users\\athar\\Downloads\\Model Doc\\app.py", "source_location": "L380", "weight": 1.0}, {"source": "c_users_athar_downloads_model_doc_app_py", "target": "app_get_runtime_status", "relation": "contains", "confidence": "EXTRACTED", "source_file": "C:\\Users\\athar\\Downloads\\Model Doc\\app.py", "source_location": "L395", "weight": 1.0}, {"source": "c_users_athar_downloads_model_doc_app_py", "target": "app_render_section_intro", "relation": "contains", "confidence": "EXTRACTED", "source_file": "C:\\Users\\athar\\Downloads\\Model Doc\\app.py", "source_location": "L425", "weight": 1.0}, {"source": "c_users_athar_downloads_model_doc_app_py", "target": "app_render_sidebar_status", "relation": "contains", "confidence": "EXTRACTED", "source_file": "C:\\Users\\athar\\Downloads\\Model Doc\\app.py", "source_location": "L438", "weight": 1.0}, {"source": "c_users_athar_downloads_model_doc_app_py", "target": "app_render_hero", "relation": "contains", "confidence": "EXTRACTED", "source_file": "C:\\Users\\athar\\Downloads\\Model Doc\\app.py", "source_location": "L464", "weight": 1.0}, {"source": "c_users_athar_downloads_model_doc_app_py", "target": "app_render_result_banner", "relation": "contains", "confidence": "EXTRACTED", "source_file": "C:\\Users\\athar\\Downloads\\Model Doc\\app.py", "source_location": "L508", "weight": 1.0}, {"source": "c_users_athar_downloads_model_doc_app_py", "target": "app_render_capture_tips", "relation": "contains", "confidence": "EXTRACTED", "source_file": "C:\\Users\\athar\\Downloads\\Model Doc\\app.py", "source_location": "L534", "weight": 1.0}, {"source": "c_users_athar_downloads_model_doc_app_py", "target": "app_render_fast_hosted_demo", "relation": "contains", "confidence": "EXTRACTED", "source_file": "C:\\Users\\athar\\Downloads\\Model Doc\\app.py", "source_location": "L552", "weight": 1.0}, {"source": "c_users_athar_downloads_model_doc_app_py", "target": "lora_finetune", "relation": "imports_from", "confidence": "EXTRACTED", "source_file": "C:\\Users\\athar\\Downloads\\Model Doc\\app.py", "source_location": "L639", "weight": 1.0}, {"source": "app_get_runtime_status", "target": "app_load_rag_chunk_count", "relation": "calls", "confidence": "EXTRACTED", "source_file": "C:\\Users\\athar\\Downloads\\Model Doc\\app.py", "source_location": "L402", "weight": 1.0}, {"source": "app_render_fast_hosted_demo", "target": "app_render_section_intro", "relation": "calls", "confidence": "EXTRACTED", "source_file": "C:\\Users\\athar\\Downloads\\Model Doc\\app.py", "source_location": "L554", "weight": 1.0}, {"source": "app_rationale_1", "target": "c_users_athar_downloads_model_doc_app_py", "relation": "rationale_for", "confidence": "EXTRACTED", "source_file": "C:\\Users\\athar\\Downloads\\Model Doc\\app.py", "source_location": "L1", "weight": 1.0}, {"source": "app_rationale_356", "target": "app_init_local_stack", "relation": "rationale_for", "confidence": "EXTRACTED", "source_file": "C:\\Users\\athar\\Downloads\\Model Doc\\app.py", "source_location": "L356", "weight": 1.0}, {"source": "app_rationale_376", "target": "app_get_feedback_collector", "relation": "rationale_for", "confidence": "EXTRACTED", "source_file": "C:\\Users\\athar\\Downloads\\Model Doc\\app.py", "source_location": "L376", "weight": 1.0}, {"source": "app_rationale_396", "target": "app_get_runtime_status", "relation": "rationale_for", "confidence": "EXTRACTED", "source_file": "C:\\Users\\athar\\Downloads\\Model Doc\\app.py", "source_location": "L396", "weight": 1.0}, {"source": "app_rationale_553", "target": "app_render_fast_hosted_demo", "relation": "rationale_for", "confidence": "EXTRACTED", "source_file": "C:\\Users\\athar\\Downloads\\Model Doc\\app.py", "source_location": "L553", "weight": 1.0}], "raw_calls": [{"caller_nid": "app_init_local_stack", "callee": "PhysicsProxiesExtractor", "source_file": "C:\\Users\\athar\\Downloads\\Model Doc\\app.py", "source_location": "L357"}, {"caller_nid": "app_init_local_stack", "callee": "VisionRAGPipeline", "source_file": "C:\\Users\\athar\\Downloads\\Model Doc\\app.py", "source_location": "L363"}, {"caller_nid": "app_get_feedback_collector", "callee": "FeedbackCollector", "source_file": "C:\\Users\\athar\\Downloads\\Model Doc\\app.py", "source_location": "L377"}, {"caller_nid": "app_load_rag_chunk_count", "callee": "Path", "source_file": "C:\\Users\\athar\\Downloads\\Model Doc\\app.py", "source_location": "L381"}, {"caller_nid": "app_load_rag_chunk_count", "callee": "exists", "source_file": "C:\\Users\\athar\\Downloads\\Model Doc\\app.py", "source_location": "L382"}, {"caller_nid": "app_load_rag_chunk_count", "callee": "open", "source_file": "C:\\Users\\athar\\Downloads\\Model Doc\\app.py", "source_location": "L385"}, {"caller_nid": "app_load_rag_chunk_count", "callee": "load", "source_file": "C:\\Users\\athar\\Downloads\\Model Doc\\app.py", "source_location": "L386"}, {"caller_nid": "app_load_rag_chunk_count", "callee": "isinstance", "source_file": "C:\\Users\\athar\\Downloads\\Model Doc\\app.py", "source_location": "L387"}, {"caller_nid": "app_load_rag_chunk_count", "callee": "get", "source_file": "C:\\Users\\athar\\Downloads\\Model Doc\\app.py", "source_location": "L388"}, {"caller_nid": "app_load_rag_chunk_count", "callee": "len", "source_file": "C:\\Users\\athar\\Downloads\\Model Doc\\app.py", "source_location": "L389"}, {"caller_nid": "app_load_rag_chunk_count", "callee": "isinstance", "source_file": "C:\\Users\\athar\\Downloads\\Model Doc\\app.py", "source_location": "L389"}, {"caller_nid": "app_get_runtime_status", "callee": "get", "source_file": "C:\\Users\\athar\\Downloads\\Model Doc\\app.py", "source_location": "L405"}, {"caller_nid": "app_get_runtime_status", "callee": "raise_for_status", "source_file": "C:\\Users\\athar\\Downloads\\Model Doc\\app.py", "source_location": "L406"}, {"caller_nid": "app_get_runtime_status", "callee": "get", "source_file": "C:\\Users\\athar\\Downloads\\Model Doc\\app.py", "source_location": "L408"}, {"caller_nid": "app_get_runtime_status", "callee": "get", "source_file": "C:\\Users\\athar\\Downloads\\Model Doc\\app.py", "source_location": "L409"}, {"caller_nid": "app_get_runtime_status", "callee": "json", "source_file": "C:\\Users\\athar\\Downloads\\Model Doc\\app.py", "source_location": "L409"}, {"caller_nid": "app_get_runtime_status", "callee": "isinstance", "source_file": "C:\\Users\\athar\\Downloads\\Model Doc\\app.py", "source_location": "L410"}, {"caller_nid": "app_get_runtime_status", "callee": "any", "source_file": "C:\\Users\\athar\\Downloads\\Model Doc\\app.py", "source_location": "L413"}, {"caller_nid": "app_get_runtime_status", "callee": "lower", "source_file": "C:\\Users\\athar\\Downloads\\Model Doc\\app.py", "source_location": "L413"}, {"caller_nid": "app_get_runtime_status", "callee": "lower", "source_file": "C:\\Users\\athar\\Downloads\\Model Doc\\app.py", "source_location": "L413"}, {"caller_nid": "app_render_section_intro", "callee": "markdown", "source_file": "C:\\Users\\athar\\Downloads\\Model Doc\\app.py", "source_location": "L426"}, {"caller_nid": "app_render_section_intro", "callee": "escape", "source_file": "C:\\Users\\athar\\Downloads\\Model Doc\\app.py", "source_location": "L429"}, {"caller_nid": "app_render_section_intro", "callee": "escape", "source_file": "C:\\Users\\athar\\Downloads\\Model Doc\\app.py", "source_location": "L430"}, {"caller_nid": "app_render_section_intro", "callee": "escape", "source_file": "C:\\Users\\athar\\Downloads\\Model Doc\\app.py", "source_location": "L431"}, {"caller_nid": "app_render_sidebar_status", "callee": "markdown", "source_file": "C:\\Users\\athar\\Downloads\\Model Doc\\app.py", "source_location": "L440"}, {"caller_nid": "app_render_sidebar_status", "callee": "escape", "source_file": "C:\\Users\\athar\\Downloads\\Model Doc\\app.py", "source_location": "L444"}, {"caller_nid": "app_render_sidebar_status", "callee": "escape", "source_file": "C:\\Users\\athar\\Downloads\\Model Doc\\app.py", "source_location": "L445"}, {"caller_nid": "app_render_hero", "callee": "markdown", "source_file": "C:\\Users\\athar\\Downloads\\Model Doc\\app.py", "source_location": "L466"}, {"caller_nid": "app_render_hero", "callee": "escape", "source_file": "C:\\Users\\athar\\Downloads\\Model Doc\\app.py", "source_location": "L476"}, {"caller_nid": "app_render_result_banner", "callee": "get", "source_file": "C:\\Users\\athar\\Downloads\\Model Doc\\app.py", "source_location": "L512"}, {"caller_nid": "app_render_result_banner", "callee": "markdown", "source_file": "C:\\Users\\athar\\Downloads\\Model Doc\\app.py", "source_location": "L519"}, {"caller_nid": "app_render_result_banner", "callee": "escape", "source_file": "C:\\Users\\athar\\Downloads\\Model Doc\\app.py", "source_location": "L525"}, {"caller_nid": "app_render_result_banner", "callee": "escape", "source_file": "C:\\Users\\athar\\Downloads\\Model Doc\\app.py", "source_location": "L526"}, {"caller_nid": "app_render_capture_tips", "callee": "markdown", "source_file": "C:\\Users\\athar\\Downloads\\Model Doc\\app.py", "source_location": "L535"}, {"caller_nid": "app_render_fast_hosted_demo", "callee": "columns", "source_file": "C:\\Users\\athar\\Downloads\\Model Doc\\app.py", "source_location": "L559"}, {"caller_nid": "app_render_fast_hosted_demo", "callee": "metric", "source_file": "C:\\Users\\athar\\Downloads\\Model Doc\\app.py", "source_location": "L560"}, {"caller_nid": "app_render_fast_hosted_demo", "callee": "metric", "source_file": "C:\\Users\\athar\\Downloads\\Model Doc\\app.py", "source_location": "L561"}, {"caller_nid": "app_render_fast_hosted_demo", "callee": "metric", "source_file": "C:\\Users\\athar\\Downloads\\Model Doc\\app.py", "source_location": "L562"}, {"caller_nid": "app_render_fast_hosted_demo", "callee": "link_button", "source_file": "C:\\Users\\athar\\Downloads\\Model Doc\\app.py", "source_location": "L563"}, {"caller_nid": "app_render_fast_hosted_demo", "callee": "markdown", "source_file": "C:\\Users\\athar\\Downloads\\Model Doc\\app.py", "source_location": "L568"}, {"caller_nid": "app_render_fast_hosted_demo", "callee": "html", "source_file": "C:\\Users\\athar\\Downloads\\Model Doc\\app.py", "source_location": "L579"}]}